jupyter_splitview/__init__.py
jupyter_splitview/inject.py
jupyter_splitview/inject_dependencies.html
jupyter_splitview/inject_split.html
jupyter_splitview/sw_cellmagic.py
vendor/compare_view/browser_compare_view.js
jupyter_splitview-0.1.1.dist-info/LICENSE
jupyter_splitview-0.1.1.dist-info/WHEEL
jupyter_splitview-0.1.1.dist-info/METADATA
jupyter_splitview-0.1.1.dist-info/RECORD
