Metadata-Version: 2.1
Name: jupyter-splitview
Version: 0.1.1
Summary: Making before/after image sliders in JupyterLab
License: MIT
Author: kolibril13
Author-email: 44469195+kolibril13@users.noreply.github.com
Requires-Python: >=3.8,<3.11
Classifier: License :: OSI Approved :: MIT License
Classifier: Programming Language :: Python :: 3
Classifier: Programming Language :: Python :: 3.10
Classifier: Programming Language :: Python :: 3.8
Classifier: Programming Language :: Python :: 3.9
Requires-Dist: Jinja2 (>=3.1.2)
Requires-Dist: Pillow (>=9.1.0)
Requires-Dist: ipykernel (>=5.0.0)
Requires-Dist: ipython (>=6.0.0)
